analyser/__init__.py
analyser/main.py
analyser/web-analyser.py
analyser/helpers/__init__.py
analyser/helpers/analysis.py
analyser/helpers/recon.py
analyser/utils/__init__.py
analyser/utils/constants.py
analyser/utils/context.py
analyser/utils/log.py
analyser/utils/utils.py
ctf_website_analyser-0.0.1.dist-info/LICENSE
ctf_website_analyser-0.0.1.dist-info/METADATA
ctf_website_analyser-0.0.1.dist-info/WHEEL
ctf_website_analyser-0.0.1.dist-info/top_level.txt
ctf_website_analyser-0.0.1.dist-info/RECORD
