Metadata-Version: 2.1
Name: ctf-website-analyser
Version: 0.0.1
Summary: A tool to analyse websites for CTF challenges
Home-page: https://github.com/ir0nstone/web-analyser
Author: ir0nstone
Author-email: bobbiusbobety@gmail.com
License: UNKNOWN
Platform: UNKNOWN
Classifier: Programming Language :: Python :: 3
Classifier: License :: OSI Approved :: MIT License
Classifier: Operating System :: OS Independent
Requires-Python: >=3.6
